CMakeLists.txt
GITHASH
LICENSE
MANIFEST.in
PYREADME.rst
README.md
setup.py
./pyHiGHS/src/HConfig.h
./pyHiGHS/src/highs_wrapper.cpp
./src/interfaces/highs_c_api.cpp
./src/interfaces/highs_c_api.h
./src/io/Filereader.cpp
./src/io/Filereader.h
./src/io/FilereaderEms.cpp
./src/io/FilereaderEms.h
./src/io/FilereaderLp.cpp
./src/io/FilereaderLp.h
./src/io/FilereaderMps.cpp
./src/io/FilereaderMps.h
./src/io/HMPSIO.cpp
./src/io/HMPSIO.h
./src/io/HMpsFF.cpp
./src/io/HMpsFF.h
./src/io/HToyIO.cpp
./src/io/HToyIO.h
./src/io/HToyIO_C.h
./src/io/HighsIO.cpp
./src/io/HighsIO.h
./src/io/LoadOptions.cpp
./src/io/LoadOptions.h
./src/io/LoadProblem.cpp
./src/io/LoadProblem.h
./src/ipm/basiclu/src/basiclu_factorize.c
./src/ipm/basiclu/src/basiclu_get_factors.c
./src/ipm/basiclu/src/basiclu_initialize.c
./src/ipm/basiclu/src/basiclu_object.c
./src/ipm/basiclu/src/basiclu_solve_dense.c
./src/ipm/basiclu/src/basiclu_solve_for_update.c
./src/ipm/basiclu/src/basiclu_solve_sparse.c
./src/ipm/basiclu/src/basiclu_update.c
./src/ipm/basiclu/src/lu_build_factors.c
./src/ipm/basiclu/src/lu_condest.c
./src/ipm/basiclu/src/lu_def.h
./src/ipm/basiclu/src/lu_dfs.c
./src/ipm/basiclu/src/lu_factorize_bump.c
./src/ipm/basiclu/src/lu_file.c
./src/ipm/basiclu/src/lu_file.h
./src/ipm/basiclu/src/lu_garbage_perm.c
./src/ipm/basiclu/src/lu_initialize.c
./src/ipm/basiclu/src/lu_internal.c
./src/ipm/basiclu/src/lu_internal.h
./src/ipm/basiclu/src/lu_list.h
./src/ipm/basiclu/src/lu_markowitz.c
./src/ipm/basiclu/src/lu_matrix_norm.c
./src/ipm/basiclu/src/lu_pivot.c
./src/ipm/basiclu/src/lu_residual_test.c
./src/ipm/basiclu/src/lu_setup_bump.c
./src/ipm/basiclu/src/lu_singletons.c
./src/ipm/basiclu/src/lu_solve_dense.c
./src/ipm/basiclu/src/lu_solve_for_update.c
./src/ipm/basiclu/src/lu_solve_sparse.c
./src/ipm/basiclu/src/lu_solve_symbolic.c
./src/ipm/basiclu/src/lu_solve_triangular.c
./src/ipm/basiclu/src/lu_update.c
./src/ipm/ipx/src/basiclu_kernel.cc
./src/ipm/ipx/src/basiclu_kernel.h
scikit_highs.egg-info/PKG-INFO
scikit_highs.egg-info/SOURCES.txt
scikit_highs.egg-info/dependency_links.txt
scikit_highs.egg-info/top_level.txt
