Metadata-Version: 1.0
Name: scikit-highs
Version: 0.5.1
Summary: Cython interface to HiGHS.
Home-page: https://github.com/mckib2/HiGHS
Author: Nicholas McKibben
Author-email: nicholas.bgp@gmail.com
License: MIT
Platform: UNKNOWN
